pds/updart/VERSION.txt
pds/updart/__init__.py
pds/updart/client.py
pds/updart/tests/__init__.py
pds/updart/tests/test_client.py
pds.updart-0.1.0.dist-info/LICENSE.md
pds.updart-0.1.0.dist-info/METADATA
pds.updart-0.1.0.dist-info/NOTICE.txt
pds.updart-0.1.0.dist-info/WHEEL
pds.updart-0.1.0.dist-info/top_level.txt
pds.updart-0.1.0.dist-info/zip-safe
pds.updart-0.1.0.dist-info/RECORD
