Metadata-Version: 2.1
Name: pds.updart
Version: 0.1.0
Summary: Get Planetary Data from the Planetary Data System (PDS)
Home-page: https://github.com/NASA-PDS/updart
Download-URL: https://github.com/NASA-PDS/updart/releases/
Author: PDS
Author-email: pds_operator@jpl.nasa.gov
License: apache-2.0
Keywords: pds,planetary data,api
Classifier: Programming Language :: Python :: 3
Classifier: Programming Language :: Python :: 3.9
Classifier: License :: OSI Approved :: Apache Software License
Classifier: Operating System :: OS Independent
Requires-Python: >=3.9
License-File: LICENSE.md
License-File: NOTICE.txt
Requires-Dist: pds.api-client ~=1.5.0
Provides-Extra: dev
Requires-Dist: black ~=23.7.0 ; extra == 'dev'
Requires-Dist: flake8 ~=6.1.0 ; extra == 'dev'
Requires-Dist: flake8-bugbear ~=23.7.10 ; extra == 'dev'
Requires-Dist: flake8-docstrings ~=1.7.0 ; extra == 'dev'
Requires-Dist: pep8-naming ~=0.13.3 ; extra == 'dev'
Requires-Dist: mypy ~=1.5.1 ; extra == 'dev'
Requires-Dist: pydocstyle ~=6.3.0 ; extra == 'dev'
Requires-Dist: coverage ~=7.3.0 ; extra == 'dev'
Requires-Dist: pytest ~=7.4.0 ; extra == 'dev'
Requires-Dist: pytest-cov ~=4.1.0 ; extra == 'dev'
Requires-Dist: pytest-watch ~=4.2.0 ; extra == 'dev'
Requires-Dist: pytest-xdist ~=3.3.1 ; extra == 'dev'
Requires-Dist: pre-commit ~=3.3.3 ; extra == 'dev'
Requires-Dist: sphinx ~=7.2.6 ; extra == 'dev'
Requires-Dist: sphinx-rtd-theme ~=2.0.0 ; extra == 'dev'
Requires-Dist: tox ~=4.11.0 ; extra == 'dev'
Requires-Dist: types-setuptools ~=68.1.0.0 ; extra == 'dev'
Requires-Dist: Jinja2 <3.1 ; extra == 'dev'
